[
    {
        "type": "portfolio",
        "children": [
            {
                "id": 1,
                "title": "Awesome Product",
                "filter": "app",
                "description": "Lorem ipsum dolor sit amet consectetur adipisicing elit.",
                "src": "inner-page/product/1.jpg"
            },
            {
                "id": 2,
                "title": "Awesome Product",
                "filter": "web",
                "description": "Lorem ipsum dolor sit amet consectetur adipisicing elit.",
                "src": "inner-page/product/2.jpg"
            },
            {
                "id": 3,
                "title": "Awesome Product",
                "filter": "card",
                "description": "Lorem ipsum dolor sit amet consectetur adipisicing elit.",
                "src": "inner-page/product/3.jpg"
            },
            {
                "id": 4,
                "title": "Awesome Product",
                "filter": "app",
                "description": "Lorem ipsum dolor sit amet consectetur adipisicing elit.",
                "src": "inner-page/product/4.jpg"
            },
            {
                "id": 5,
                "title": "Awesome Product",
                "filter": "card",
                "description": "Lorem ipsum dolor sit amet consectetur adipisicing elit.",
                "src": "inner-page/product/5.jpg"
            },
            {
                "id": 6,
                "title": "Awesome Product",
                "filter": "app",
                "description": "Lorem ipsum dolor sit amet consectetur adipisicing elit.",
                "src": "inner-page/product/6.jpg"
            },
            {
                "id": 7,
                "title": "Awesome Product",
                "filter": "web",
                "description": "Lorem ipsum dolor sit amet consectetur adipisicing elit.",
                "src": "inner-page/product/7.jpg"
            },
            {
                "id": 8,
                "title": "Awesome Product",
                "filter": "card",
                "description": "Lorem ipsum dolor sit amet consectetur adipisicing elit.",
                "src": "inner-page/product/8.jpg"
            },
            {
                "id": 9,
                "title": "Awesome Product",
                "filter": "app",
                "description": "Lorem ipsum dolor sit amet consectetur adipisicing elit.",
                "src": "inner-page/product/9.jpg"
            },
            {
                "id": 10,
                "title": "Awesome Product",
                "filter": "web",
                "description": "Lorem ipsum dolor sit amet consectetur adipisicing elit.",
                "src": "inner-page/product/10.jpg"
            },
            {
                "id": 11,
                "title": "Awesome Product",
                "filter": "app",
                "description": "Lorem ipsum dolor sit amet consectetur adipisicing elit.",
                "src": "inner-page/product/11.jpg"
            },
            {
                "id": 12,
                "title": "Awesome Product",
                "filter": "card",
                "description": "Lorem ipsum dolor sit amet consectetur adipisicing elit.",
                "src": "inner-page/product/12.jpg"
            }
        ]
    }
]